[{"summoner_id":439,"monster_1_id":425,"monster_2_id":372,"monster_3_id":373,"monster_4_id":371,"monster_5_id":429,"monster_6_id":194,"ruleset":"Fog of War","mana_cap":42,"tot":38,"ratio":71.05},{"summoner_id":439,"monster_1_id":184,"monster_2_id":372,"monster_3_id":194,"monster_4_id":373,"monster_5_id":429,"monster_6_id":371,"ruleset":"Fog of War","mana_cap":42,"tot":21,"ratio":61.9},{"summoner_id":441,"monster_1_id":152,"monster_2_id":190,"monster_3_id":423,"monster_4_id":416,"monster_5_id":148,"monster_6_id":417,"ruleset":"Fog of War","mana_cap":42,"tot":27,"ratio":48.15},{"summoner_id":145,"monster_1_id":361,"monster_2_id":190,"monster_3_id":425,"monster_4_id":357,"monster_5_id":360,"monster_6_id":192,"ruleset":"Fog of War","mana_cap":42,"tot":12,"ratio":0},{"summoner_id":16,"monster_1_id":213,"monster_2_id":339,"monster_3_id":98,"monster_4_id":131,"monster_5_id":280,"monster_6_id":18,"ruleset":"Fog of War","mana_cap":42,"tot":9,"ratio":0},{"summoner_id":439,"monster_1_id":372,"monster_2_id":373,"monster_3_id":371,"monster_4_id":430,"monster_5_id":90,"monster_6_id":186,"ruleset":"Fog of War","mana_cap":42,"tot":8,"ratio":0},{"summoner_id":49,"monster_1_id":55,"monster_2_id":125,"monster_3_id":92,"monster_4_id":53,"monster_5_id":91,"monster_6_id":144,"ruleset":"Fog of War","mana_cap":42,"tot":8,"ratio":0},{"summoner_id":16,"monster_1_id":388,"monster_2_id":339,"monster_3_id":98,"monster_4_id":338,"monster_5_id":387,"monster_6_id":429,"ruleset":"Fog of War","mana_cap":42,"tot":8,"ratio":0},{"summoner_id":438,"monster_1_id":140,"monster_2_id":52,"monster_3_id":92,"monster_4_id":245,"monster_5_id":360,"monster_6_id":192,"ruleset":"Fog of War","mana_cap":42,"tot":8,"ratio":0},{"summoner_id":291,"monster_1_id":55,"monster_2_id":125,"monster_3_id":92,"monster_4_id":52,"monster_5_id":352,"monster_6_id":215,"ruleset":"Fog of War","mana_cap":42,"tot":8,"ratio":0},{"summoner_id":439,"monster_1_id":368,"monster_2_id":253,"monster_3_id":373,"monster_4_id":371,"monster_5_id":429,"monster_6_id":372,"ruleset":"Fog of War","mana_cap":42,"tot":8,"ratio":0},{"summoner_id":236,"monster_1_id":166,"monster_2_id":299,"monster_3_id":196,"monster_4_id":164,"monster_5_id":158,"monster_6_id":163,"ruleset":"Fog of War","mana_cap":42,"tot":7,"ratio":0},{"summoner_id":259,"monster_1_id":334,"monster_2_id":184,"monster_3_id":279,"monster_4_id":186,"monster_5_id":377,"monster_6_id":28,"ruleset":"Fog of War","mana_cap":42,"tot":6,"ratio":0},{"summoner_id":236,"monster_1_id":405,"monster_2_id":247,"monster_3_id":333,"monster_4_id":400,"monster_5_id":161,"monster_6_id":163,"ruleset":"Fog of War","mana_cap":42,"tot":6,"ratio":0},{"summoner_id":441,"monster_1_id":152,"monster_2_id":146,"monster_3_id":270,"monster_4_id":234,"monster_5_id":350,"monster_6_id":417,"ruleset":"Fog of War","mana_cap":42,"tot":6,"ratio":0},{"summoner_id":291,"monster_1_id":348,"monster_2_id":347,"monster_3_id":201,"monster_4_id":179,"monster_5_id":91,"monster_6_id":242,"ruleset":"Fog of War","mana_cap":42,"tot":6,"ratio":0},{"summoner_id":49,"monster_1_id":50,"monster_2_id":294,"monster_3_id":92,"monster_4_id":341,"monster_5_id":86,"monster_6_id":215,"ruleset":"Fog of War","mana_cap":42,"tot":6,"ratio":0},{"summoner_id":16,"monster_1_id":19,"monster_2_id":339,"monster_3_id":91,"monster_4_id":280,"monster_5_id":338,"monster_6_id":"","ruleset":"Fog of War","mana_cap":42,"tot":6,"ratio":0},{"summoner_id":259,"monster_1_id":226,"monster_2_id":179,"monster_3_id":24,"monster_4_id":85,"monster_5_id":187,"monster_6_id":192,"ruleset":"Fog of War","mana_cap":42,"tot":6,"ratio":0},{"summoner_id":441,"monster_1_id":152,"monster_2_id":413,"monster_3_id":417,"monster_4_id":344,"monster_5_id":243,"monster_6_id":39,"ruleset":"Fog of War","mana_cap":42,"tot":6,"ratio":0},{"summoner_id":5,"monster_1_id":162,"monster_2_id":247,"monster_3_id":193,"monster_4_id":158,"monster_5_id":165,"monster_6_id":161,"ruleset":"Fog of War","mana_cap":42,"tot":6,"ratio":0},{"summoner_id":38,"monster_1_id":269,"monster_2_id":344,"monster_3_id":39,"monster_4_id":42,"monster_5_id":243,"monster_6_id":43,"ruleset":"Fog of War","mana_cap":42,"tot":6,"ratio":0},{"summoner_id":16,"monster_1_id":80,"monster_2_id":190,"monster_3_id":17,"monster_4_id":194,"monster_5_id":338,"monster_6_id":172,"ruleset":"Fog of War","mana_cap":42,"tot":5,"ratio":0},{"summoner_id":178,"monster_1_id":231,"monster_2_id":207,"monster_3_id":98,"monster_4_id":250,"monster_5_id":171,"monster_6_id":192,"ruleset":"Fog of War","mana_cap":42,"tot":5,"ratio":0},{"summoner_id":224,"monster_1_id":162,"monster_2_id":207,"monster_3_id":161,"monster_4_id":222,"monster_5_id":228,"monster_6_id":212,"ruleset":"Fog of War","mana_cap":42,"tot":5,"ratio":0},{"summoner_id":112,"monster_1_id":184,"monster_2_id":28,"monster_3_id":102,"monster_4_id":186,"monster_5_id":279,"monster_6_id":371,"ruleset":"Fog of War","mana_cap":42,"tot":5,"ratio":0},{"summoner_id":16,"monster_1_id":213,"monster_2_id":104,"monster_3_id":172,"monster_4_id":207,"monster_5_id":98,"monster_6_id":194,"ruleset":"Fog of War","mana_cap":42,"tot":4,"ratio":0},{"summoner_id":236,"monster_1_id":405,"monster_2_id":333,"monster_3_id":4,"monster_4_id":164,"monster_5_id":9,"monster_6_id":214,"ruleset":"Fog of War","mana_cap":42,"tot":4,"ratio":0},{"summoner_id":437,"monster_1_id":209,"monster_2_id":384,"monster_3_id":385,"monster_4_id":168,"monster_5_id":14,"monster_6_id":199,"ruleset":"Fog of War","mana_cap":42,"tot":4,"ratio":0},{"summoner_id":439,"monster_1_id":184,"monster_2_id":335,"monster_3_id":373,"monster_4_id":194,"monster_5_id":371,"monster_6_id":372,"ruleset":"Fog of War","mana_cap":42,"tot":4,"ratio":0},{"summoner_id":439,"monster_1_id":184,"monster_2_id":373,"monster_3_id":253,"monster_4_id":371,"monster_5_id":372,"monster_6_id":183,"ruleset":"Fog of War","mana_cap":42,"tot":3,"ratio":0},{"summoner_id":441,"monster_1_id":152,"monster_2_id":151,"monster_3_id":243,"monster_4_id":234,"monster_5_id":344,"monster_6_id":148,"ruleset":"Fog of War","mana_cap":42,"tot":2,"ratio":0},{"summoner_id":178,"monster_1_id":103,"monster_2_id":339,"monster_3_id":250,"monster_4_id":171,"monster_5_id":14,"monster_6_id":385,"ruleset":"Fog of War","mana_cap":42,"tot":2,"ratio":0},{"summoner_id":16,"monster_1_id":339,"monster_2_id":338,"monster_3_id":175,"monster_4_id":390,"monster_5_id":98,"monster_6_id":385,"ruleset":"Fog of War","mana_cap":42,"tot":2,"ratio":0},{"summoner_id":437,"monster_1_id":209,"monster_2_id":384,"monster_3_id":287,"monster_4_id":385,"monster_5_id":168,"monster_6_id":425,"ruleset":"Fog of War","mana_cap":42,"tot":1,"ratio":0},{"summoner_id":259,"monster_1_id":82,"monster_2_id":253,"monster_3_id":220,"monster_4_id":85,"monster_5_id":33,"monster_6_id":28,"ruleset":"Fog of War","mana_cap":42,"tot":1,"ratio":0},{"summoner_id":240,"monster_1_id":348,"monster_2_id":211,"monster_3_id":425,"monster_4_id":118,"monster_5_id":345,"monster_6_id":350,"ruleset":"Fog of War","mana_cap":42,"tot":0,"ratio":0},{"summoner_id":178,"monster_1_id":231,"monster_2_id":339,"monster_3_id":338,"monster_4_id":176,"monster_5_id":280,"monster_6_id":237,"ruleset":"Fog of War","mana_cap":42,"tot":0,"ratio":0},{"summoner_id":441,"monster_1_id":152,"monster_2_id":190,"monster_3_id":417,"monster_4_id":416,"monster_5_id":148,"monster_6_id":423,"ruleset":"Fog of War","mana_cap":42,"tot":0,"ratio":null},{"summoner_id":441,"monster_1_id":151,"monster_2_id":152,"monster_3_id":243,"monster_4_id":417,"monster_5_id":416,"monster_6_id":344,"ruleset":"Fog of War","mana_cap":42,"tot":0,"ratio":0}]