[{"summoner_id":438,"monster_1_id":91,"monster_2_id":353,"monster_3_id":50,"monster_4_id":354,"monster_5_id":92,"monster_6_id":267,"ruleset":"Earthquake","mana_cap":34,"tot":1,"ratio":0},{"summoner_id":156,"monster_1_id":413,"monster_2_id":37,"monster_3_id":343,"monster_4_id":101,"monster_5_id":421,"monster_6_id":428,"ruleset":"Earthquake","mana_cap":34,"tot":0,"ratio":0},{"summoner_id":27,"monster_1_id":226,"monster_2_id":253,"monster_3_id":249,"monster_4_id":90,"monster_5_id":183,"monster_6_id":221,"ruleset":"Earthquake","mana_cap":34,"tot":0,"ratio":0},{"summoner_id":224,"monster_1_id":226,"monster_2_id":218,"monster_3_id":220,"monster_4_id":212,"monster_5_id":186,"monster_6_id":"","ruleset":"Earthquake","mana_cap":34,"tot":0,"ratio":0},{"summoner_id":38,"monster_1_id":152,"monster_2_id":151,"monster_3_id":66,"monster_4_id":153,"monster_5_id":154,"monster_6_id":34,"ruleset":"Earthquake","mana_cap":34,"tot":0,"ratio":0},{"summoner_id":16,"monster_1_id":213,"monster_2_id":172,"monster_3_id":207,"monster_4_id":98,"monster_5_id":338,"monster_6_id":394,"ruleset":"Earthquake","mana_cap":34,"tot":0,"ratio":0},{"summoner_id":239,"monster_1_id":82,"monster_2_id":345,"monster_3_id":150,"monster_4_id":34,"monster_5_id":35,"monster_6_id":344,"ruleset":"Earthquake","mana_cap":34,"tot":0,"ratio":0},{"summoner_id":442,"monster_1_id":348,"monster_2_id":347,"monster_3_id":436,"monster_4_id":194,"monster_5_id":350,"monster_6_id":346,"ruleset":"Earthquake","mana_cap":34,"tot":0,"ratio":0},{"summoner_id":439,"monster_1_id":372,"monster_2_id":373,"monster_3_id":371,"monster_4_id":429,"monster_5_id":183,"monster_6_id":"","ruleset":"Earthquake","mana_cap":34,"tot":0,"ratio":null},{"summoner_id":439,"monster_1_id":334,"monster_2_id":373,"monster_3_id":372,"monster_4_id":429,"monster_5_id":183,"monster_6_id":185,"ruleset":"Earthquake","mana_cap":34,"tot":0,"ratio":0},{"summoner_id":224,"monster_1_id":231,"monster_2_id":339,"monster_3_id":172,"monster_4_id":250,"monster_5_id":212,"monster_6_id":"","ruleset":"Earthquake","mana_cap":34,"tot":0,"ratio":0},{"summoner_id":156,"monster_1_id":349,"monster_2_id":151,"monster_3_id":350,"monster_4_id":153,"monster_5_id":154,"monster_6_id":196,"ruleset":"Earthquake","mana_cap":34,"tot":0,"ratio":0},{"summoner_id":437,"monster_1_id":388,"monster_2_id":384,"monster_3_id":385,"monster_4_id":387,"monster_5_id":171,"monster_6_id":381,"ruleset":"Earthquake","mana_cap":34,"tot":0,"ratio":null},{"summoner_id":291,"monster_1_id":144,"monster_2_id":91,"monster_3_id":203,"monster_4_id":132,"monster_5_id":142,"monster_6_id":124,"ruleset":"Earthquake","mana_cap":34,"tot":0,"ratio":0},{"summoner_id":16,"monster_1_id":174,"monster_2_id":194,"monster_3_id":17,"monster_4_id":172,"monster_5_id":338,"monster_6_id":242,"ruleset":"Earthquake","mana_cap":34,"tot":0,"ratio":0},{"summoner_id":262,"monster_1_id":166,"monster_2_id":247,"monster_3_id":8,"monster_4_id":158,"monster_5_id":3,"monster_6_id":163,"ruleset":"Earthquake","mana_cap":34,"tot":0,"ratio":0},{"summoner_id":262,"monster_1_id":348,"monster_2_id":52,"monster_3_id":141,"monster_4_id":256,"monster_5_id":245,"monster_6_id":51,"ruleset":"Earthquake","mana_cap":34,"tot":0,"ratio":0},{"summoner_id":259,"monster_1_id":23,"monster_2_id":131,"monster_3_id":297,"monster_4_id":188,"monster_5_id":186,"monster_6_id":371,"ruleset":"Earthquake","mana_cap":34,"tot":0,"ratio":0},{"summoner_id":441,"monster_1_id":413,"monster_2_id":151,"monster_3_id":150,"monster_4_id":196,"monster_5_id":417,"monster_6_id":148,"ruleset":"Earthquake","mana_cap":34,"tot":0,"ratio":0},{"summoner_id":437,"monster_1_id":213,"monster_2_id":91,"monster_3_id":338,"monster_4_id":387,"monster_5_id":172,"monster_6_id":280,"ruleset":"Earthquake","mana_cap":34,"tot":0,"ratio":0},{"summoner_id":278,"monster_1_id":180,"monster_2_id":23,"monster_3_id":183,"monster_4_id":179,"monster_5_id":24,"monster_6_id":188,"ruleset":"Earthquake","mana_cap":34,"tot":0,"ratio":0},{"summoner_id":261,"monster_1_id":152,"monster_2_id":151,"monster_3_id":34,"monster_4_id":39,"monster_5_id":234,"monster_6_id":276,"ruleset":"Earthquake","mana_cap":34,"tot":0,"ratio":null},{"summoner_id":437,"monster_1_id":174,"monster_2_id":339,"monster_3_id":20,"monster_4_id":338,"monster_5_id":172,"monster_6_id":337,"ruleset":"Earthquake","mana_cap":34,"tot":0,"ratio":0},{"summoner_id":49,"monster_1_id":218,"monster_2_id":340,"monster_3_id":64,"monster_4_id":199,"monster_5_id":66,"monster_6_id":196,"ruleset":"Earthquake","mana_cap":34,"tot":0,"ratio":0},{"summoner_id":27,"monster_1_id":23,"monster_2_id":334,"monster_3_id":33,"monster_4_id":350,"monster_5_id":90,"monster_6_id":"","ruleset":"Earthquake","mana_cap":34,"tot":0,"ratio":0},{"summoner_id":254,"monster_1_id":388,"monster_2_id":177,"monster_3_id":337,"monster_4_id":83,"monster_5_id":"","monster_6_id":"","ruleset":"Earthquake","mana_cap":34,"tot":0,"ratio":0},{"summoner_id":262,"monster_1_id":180,"monster_2_id":184,"monster_3_id":374,"monster_4_id":91,"monster_5_id":192,"monster_6_id":65,"ruleset":"Earthquake","mana_cap":34,"tot":0,"ratio":0},{"summoner_id":178,"monster_1_id":213,"monster_2_id":14,"monster_3_id":280,"monster_4_id":173,"monster_5_id":196,"monster_6_id":"","ruleset":"Earthquake","mana_cap":34,"tot":0,"ratio":0},{"summoner_id":437,"monster_1_id":103,"monster_2_id":338,"monster_3_id":339,"monster_4_id":337,"monster_5_id":196,"monster_6_id":296,"ruleset":"Earthquake","mana_cap":34,"tot":0,"ratio":0}]